object_detector/__init__.py
object_detector/detect.py
object_detector/util.py
od_detect-0.1.dist-info/METADATA
od_detect-0.1.dist-info/WHEEL
od_detect-0.1.dist-info/entry_points.txt
od_detect-0.1.dist-info/top_level.txt
od_detect-0.1.dist-info/RECORD
